minipip.py
minipip-0.1b5.dist-info/LICENSE
minipip-0.1b5.dist-info/METADATA
minipip-0.1b5.dist-info/WHEEL
minipip-0.1b5.dist-info/entry_points.txt
minipip-0.1b5.dist-info/top_level.txt
minipip-0.1b5.dist-info/RECORD
